odoo/addons/stock_restrict_by_planned_consumed_date/README.rst
odoo/addons/stock_restrict_by_planned_consumed_date/__init__.py
odoo/addons/stock_restrict_by_planned_consumed_date/__manifest__.py
odoo/addons/stock_restrict_by_planned_consumed_date/i18n/fr.po
odoo/addons/stock_restrict_by_planned_consumed_date/i18n/it.po
odoo/addons/stock_restrict_by_planned_consumed_date/i18n/stock_restrict_by_planned_consumed_date.pot
odoo/addons/stock_restrict_by_planned_consumed_date/models/__init__.py
odoo/addons/stock_restrict_by_planned_consumed_date/models/stock_move.py
odoo/addons/stock_restrict_by_planned_consumed_date/models/stock_quant.py
odoo/addons/stock_restrict_by_planned_consumed_date/readme/CONTRIBUTORS.md
odoo/addons/stock_restrict_by_planned_consumed_date/readme/DESCRIPTION.md
odoo/addons/stock_restrict_by_planned_consumed_date/readme/ROADMAP.md
odoo/addons/stock_restrict_by_planned_consumed_date/static/description/icon.png
odoo/addons/stock_restrict_by_planned_consumed_date/static/description/index.html
odoo/addons/stock_restrict_by_planned_consumed_date/tests/__init__.py
odoo/addons/stock_restrict_by_planned_consumed_date/tests/test_stock_restrict_by_planned_consumed_date.py
odoo_addon_stock_restrict_by_planned_consumed_date-17.0.1.0.0.4.dist-info/METADATA
odoo_addon_stock_restrict_by_planned_consumed_date-17.0.1.0.0.4.dist-info/WHEEL
odoo_addon_stock_restrict_by_planned_consumed_date-17.0.1.0.0.4.dist-info/top_level.txt
odoo_addon_stock_restrict_by_planned_consumed_date-17.0.1.0.0.4.dist-info/RECORD
